{
  "success": true,
  "data": {
    "id": 6540,
    "name": "<p>最能概括你自己的三个词是什么？</p>",
    "options": null,
    "answer": "<p>在行为面试中，最能概括我的三个词是：</p>\n<ol>\n  <li><strong>适应性</strong> - 能够灵活应对不同的挑战和环境。</li>\n  <li><strong>团队合作</strong> - 重视与他人合作，积极支持团队目标。</li>\n  <li><strong>解决问题</strong> - 善于分析和解决复杂问题，寻找有效的解决方案。</li>\n</ol>\n<p>这三个词体现了我的工作风格和价值观。</p>",
    "type": 6,
    "level": 1,
    "freq": 0.01066062,
    "analysis": "<h3>1. 题目核心</h3>\n<ul>\n  <li><strong>问题</strong>：用三个词概括自己。</li>\n  <li><strong>考察点</strong>：\n    <ul>\n      <li>求职者对自身优势、特点的清晰认知。</li>\n      <li>求职者的语言概括能力和表达能力。</li>\n      <li>所选择的词与应聘岗位的匹配度，以此判断求职者是否适合该岗位。</li>\n    </ul>\n  </li>\n</ul>\n<h3>2. 背景知识</h3>\n<ul>\n  <li>在行为面试中，此类问题旨在让面试官快速了解求职者的个人特质。不同岗位通常对应不同的理想特质，例如技术岗位可能更看重严谨、创新、专注；销售岗位可能更看重沟通能力、热情、抗压能力等。</li>\n</ul>\n<h3>3. 解析</h3>\n<h4>（1）如何选择合适的三个词</h4>\n<ul>\n  <li><strong>结合岗位要求</strong>：深入研究招聘信息中对岗位的职责描述和所需技能、特质，选择与之相关的词。比如应聘程序员岗位，可选择“严谨”“高效”“创新”。</li>\n  <li><strong>突出个人优势</strong>：从自己过往的学习、工作经历中提炼出能体现自身价值的特质。例如有成功完成复杂项目的经验，可选择“坚韧”“负责”“协作”。</li>\n  <li><strong>具有独特性</strong>：避免选择过于常见、缺乏个性的词，如“善良”“诚实”，要选择能真正展现自己与众不同之处的词。</li>\n</ul>\n<h4>（2）解释所选词汇</h4>\n<ul>\n  <li>仅仅说出三个词是不够的，还需要用具体事例来解释每个词。通过事例能让面试官更直观地了解这些特质在你身上的体现，增强可信度。</li>\n</ul>\n<h4>（3）保持一致性</h4>\n<ul>\n  <li>所选择的三个词之间要相互关联、协调，共同构成一个完整、正面的个人形象，不能出现前后矛盾的情况。</li>\n</ul>\n<h3>4. 示例回答</h3>\n<p>\n  假设应聘的是市场营销岗位：\n  “我认为最能概括我的三个词是‘敏锐’‘创意’和‘坚韧’。\n</p>\n<p>‘敏锐’体现在我对市场动态和消费者需求有着很强的洞察力。之前在参与一个新产品推广项目时，我通过对市场数据的深入分析和对消费者行为的观察，敏锐地捕捉到了一个潜在的市场机会，及时调整了推广策略，最终使产品的市场占有率有了显著提升。</p>\n<p>‘创意’是我在工作中的一大优势。在策划营销活动时，我总是能想出新颖独特的点子。有一次为了推广一款运动产品，我策划了一场线上线下结合的互动活动，将运动挑战与社交分享相结合，吸引了大量用户参与，大大提高了产品的知名度。</p>\n<p>‘坚韧’则让我在面对困难和挑战时从不轻易放弃。在一个时间紧迫、资源有限的项目中，我们遇到了很多难题，如合作伙伴突然退出、预算超支等。但我始终保持积极的心态，带领团队一起努力寻找解决方案，最终成功完成了项目目标。”</p>\n<h3>5. 常见误区</h3>\n<h4>（1）选择与岗位无关的词</h4>\n<ul>\n  <li>误区：没有考虑岗位需求，随意选择一些与工作能力、岗位特质无关的词，如“幽默”“随和”等。</li>\n  <li>纠正：紧密围绕岗位要求来选择能体现自己工作能力和职业素养的词。</li>\n</ul>\n<h4>（2）只说词不解释</h4>\n<ul>\n  <li>误区：只是简单地说出三个词，没有用具体事例进行说明，显得空洞、缺乏说服力。</li>\n  <li>纠正：为每个词搭配一个具体的事例，详细阐述这些特质在实际工作或学习中的体现。</li>\n</ul>\n<h4>（3）选择相互矛盾的词</h4>\n<ul>\n  <li>误区：所选的三个词之间存在逻辑冲突，如“冲动”和“谨慎”同时出现。</li>\n  <li>纠正：确保三个词相互协调、统一，共同塑造一个积极正面的个人形象。</li>\n</ul>\n<h3>6. 总结回答</h3>\n<p>在回答“最能概括你自己的三个词是什么”这个问题时，要先结合应聘岗位的要求，选择能突出自身优势且具有独特性的三个词。然后用具体事例详细解释每个词，展现这些特质在实际中的体现。同时要注意所选词汇之间的一致性，避免出现矛盾。最后清晰、有条理地表达出来，让面试官全面、深入地了解你的个人特质。</p>",
    "more_ask": "<p>面试官可能会进一步问：</p>\n<ol>\n  <li>\n    <p>能力</p>\n    <ul>\n      <li>提示：能否举一个具体例子，展示你是如何运用这项能力解决问题的？</li>\n    </ul>\n  </li>\n  <li>\n    <p>适应性</p>\n    <ul>\n      <li>提示：请分享一次你面对变化时的经历，你是如何调整自己的？</li>\n    </ul>\n  </li>\n  <li>\n    <p>合作</p>\n    <ul>\n      <li>提示：描述一个团队项目中，你是如何与他人协作并克服冲突的？</li>\n    </ul>\n  </li>\n</ol>\n<p>进一步深问的问题：</p>\n<ol>\n  <li>\n    <p>你在这个经历中学到了什么？如何影响你后来的工作？</p>\n    <ul>\n      <li>提示：探讨其长期影响与反思。</li>\n    </ul>\n  </li>\n  <li>\n    <p>你认为自己在这项能力上是否还有提升空间？如果有，你打算如何改善？</p>\n    <ul>\n      <li>提示：关注自我认知与发展计划。</li>\n    </ul>\n  </li>\n  <li>\n    <p>这个团队项目的结果如何？你认为自己的贡献关键在哪里？</p>\n    <ul>\n      <li>提示：深入探讨成果与个人影响。</li>\n    </ul>\n  </li>\n</ol>",
    "mindmap": "mindmap\n  root((行为面试中的三个关键特质))\n    适应性\n      灵活应对不同的挑战\n      适应不同环境\n    团队合作\n      重视与他人合作\n      积极支持团队目标\n    解决问题\n      分析复杂问题\n      寻找有效解决方案",
    "keynote": "- 适应性：灵活应对挑战，适应新环境\n- 团队合作：重视合作，支持团队目标\n- 解决问题：分析问题，寻找解决方案",
    "group_id": 19,
    "kps": [
      "自我认知",
      "个性和生活态度"
    ],
    "years": [
      2025,
      2024,
      2023,
      2022
    ],
    "corps": [
      "字节跳动",
      "三七互娱",
      "华为",
      "网易",
      "数字马力",
      "Shopee虾皮",
      "帆软",
      "童心制物",
      "尹兆科技",
      "快手",
      "腾讯",
      "百度",
      "深信服",
      "游卡",
      "拼多多",
      "安克创新",
      "美团",
      "广州百田",
      "天地伟业",
      "瑞幸",
      "微鲤科技",
      "招银网络科技",
      "淘天集团",
      "招商银行",
      "阿里云",
      "vivo",
      "华创微",
      "OPPO",
      "京东",
      "科大讯飞",
      "度小满",
      "钉钉",
      "阿里国际",
      "小米",
      "中兴通讯",
      "滴滴",
      "某小厂",
      "携程",
      "CVTE视源股份",
      "蚂蚁集团",
      "用友",
      "同程旅行",
      "字节抖音",
      "360",
      "猿辅导",
      "金山",
      "饿了么",
      "中国系统",
      "影石Insta360",
      "贝壳",
      "大华",
      "4399",
      "潮流网络",
      "中国移动",
      "顺丰",
      "字节飞书",
      "卫翎科技",
      "好未来",
      "腾讯音乐",
      "途虎养车",
      "商洛移动",
      "美团优选",
      "深圳数马电子",
      "禾赛科技",
      "致同",
      "思摩尔国际",
      "上海禾赛科技有限公司"
    ]
  }
}